zephyr/__init__.py
zephyr/bin/zephyr
zephyr/zephyr_cli/__init__.py
zephyr/zephyr_cli/cli.py
zephyr/zephyr_commands/__init__.py
zephyr/zephyr_config/__init__.py
zephyr/zephyr_config/config.py
zephyr/zephyr_state/__init__.py
zephyr/zephyr_state/zephyr_state.py
zephyr/zephyr_utils/__init__.py
zephyr/zephyr_utils/init_utils.py
zephyr/zephyr_utils/module_utils.py
zephyr/zephyr_utils/pipeline_utils.py
zephyr/zephyr_utils/zephyr_utils.py
zephyr_bootstrap-0.0.2.data/scripts/zephyr
zephyr_bootstrap-0.0.2.dist-info/LICENSE
zephyr_bootstrap-0.0.2.dist-info/METADATA
zephyr_bootstrap-0.0.2.dist-info/WHEEL
zephyr_bootstrap-0.0.2.dist-info/top_level.txt
zephyr_bootstrap-0.0.2.dist-info/RECORD
