Metadata-Version: 2.1
Name: zephyr-bootstrap
Version: 0.0.2
Summary: Zephyr is a command-line utility that provides project and component scaffolding to build modular pipelines
Home-page: https://github.com/banjtheman/zephyr
Author: Banjo Obayomi
Author-email: banjtheman@gmail.com
License: UNKNOWN
Keywords: python,pipeline,metaflow,cookiecutter,docker
Platform: UNKNOWN
Classifier: Development Status :: 4 - Beta
Classifier: Intended Audience :: Developers
Classifier: Natural Language :: English
Classifier: Programming Language :: Python
Classifier: Programming Language :: Python :: 3
Classifier: Programming Language :: Python :: 3.6
Classifier: Programming Language :: Python :: 3.7
Classifier: Programming Language :: Python :: 3.8
Requires-Python: >3.6
Requires-Dist: click
Requires-Dist: nbformat
Requires-Dist: cookiecutter
